dataknobs_common/__init__.py
dataknobs_common/exceptions.py
dataknobs_common/py.typed
dataknobs_common/registry.py
dataknobs_common/serialization.py
dataknobs_common/testing.py
dataknobs_common/events/__init__.py
dataknobs_common/events/bus.py
dataknobs_common/events/memory.py
dataknobs_common/events/postgres.py
dataknobs_common/events/redis.py
dataknobs_common/events/types.py
dataknobs_common-1.2.1.dist-info/METADATA
dataknobs_common-1.2.1.dist-info/WHEEL
dataknobs_common-1.2.1.dist-info/RECORD
