Metadata-Version: 2.4
Name: dataknobs-common
Version: 1.2.1
Summary: Common utilities and base classes for dataknobs packages
Author-email: Spence Koehler <KoehlerSB747@gmail.com>
Requires-Python: >=3.10
